parametric/__init__.py
parametric/_base_params.py
parametric/_context_manager.py
parametric/_field_eq_check.py
parametric/_validate.py
parametric-0.11.1.dist-info/LICENSE
parametric-0.11.1.dist-info/METADATA
parametric-0.11.1.dist-info/WHEEL
parametric-0.11.1.dist-info/top_level.txt
parametric-0.11.1.dist-info/RECORD
