Metadata-Version: 2.2
Name: parametric
Version: 0.11.1
Summary: A simple package for parameterization
Author: Yoni Chechik
License:                                  Apache License
Project-URL: Homepage, https://github.com/YoniChechik/parametric
Classifier: Development Status :: 5 - Production/Stable
Classifier: Intended Audience :: Developers
Classifier: Intended Audience :: Science/Research
Classifier: Programming Language :: Python :: 3
Classifier: Programming Language :: Python :: 3.10
Classifier: Programming Language :: Python :: 3.11
Classifier: Programming Language :: Python :: 3.12
Classifier: Programming Language :: Python :: 3.13
Classifier: Topic :: Software Development :: Libraries :: Python Modules
Classifier: Topic :: Scientific/Engineering :: Information Analysis
Classifier: Topic :: Scientific/Engineering :: Artificial Intelligence
Classifier: Topic :: Software Development :: Libraries
Classifier: Topic :: Software Development :: Libraries :: Application Frameworks
Classifier: Topic :: Software Development :: Libraries :: Python Modules
Classifier: Operating System :: OS Independent
Classifier: Natural Language :: English
Requires-Python: <3.14,>=3.10
License-File: LICENSE
Requires-Dist: msgpack
Requires-Dist: numpy
Requires-Dist: pydantic>=2
Requires-Dist: pyyaml
